setup.py
prob_dsn/Binomialdistribution.py
prob_dsn/Gaussiandistribution.py
prob_dsn/Generaldistribution.py
prob_dsn/__init__.py
prob_dsn.egg-info/PKG-INFO
prob_dsn.egg-info/SOURCES.txt
prob_dsn.egg-info/dependency_links.txt
prob_dsn.egg-info/not-zip-safe
prob_dsn.egg-info/top_level.txt