Metadata-Version: 1.0
Name: prob-dsn
Version: 0.1
Summary: Probability Distributions
Home-page: UNKNOWN
Author: Seyifunmi Owoeye
Author-email: seyifunmiowoeye@gmail.com
License: UNKNOWN
Platform: UNKNOWN
